{
  "data_path": "data/ablations/h16_d50/demos.npz",
  "epochs": 30,
  "batch_size": 128,
  "diffusion_steps": 50,
  "device": "cpu",
  "lr": 0.001,
  "hidden_dim": 128,
  "action_scale": 0.07999999821186066,
  "best_val_loss": 0.3984597325325012,
  "history": [
    {
      "epoch": 1,
      "train_loss": 1.003045265674591,
      "val_loss": 1.0016251802444458
    },
    {
      "epoch": 2,
      "train_loss": 0.9903168233235677,
      "val_loss": 0.9451291561126709
    },
    {
      "epoch": 3,
      "train_loss": 0.9841845602459378,
      "val_loss": 0.9583569169044495
    },
    {
      "epoch": 4,
      "train_loss": 0.9782065873675876,
      "val_loss": 0.977511465549469
    },
    {
      "epoch": 5,
      "train_loss": 0.9390714332792494,
      "val_loss": 0.9421097636222839
    },
    {
      "epoch": 6,
      "train_loss": 0.9306060769822863,
      "val_loss": 0.9485507011413574
    },
    {
      "epoch": 7,
      "train_loss": 0.9045429878764683,
      "val_loss": 0.8900808095932007
    },
    {
      "epoch": 8,
      "train_loss": 0.8420245756043329,
      "val_loss": 0.7769827246665955
    },
    {
      "epoch": 9,
      "train_loss": 0.8206769450505574,
      "val_loss": 0.7787935733795166
    },
    {
      "epoch": 10,
      "train_loss": 0.773657115565406,
      "val_loss": 0.7463342547416687
    },
    {
      "epoch": 11,
      "train_loss": 0.7408252432611253,
      "val_loss": 0.7070243954658508
    },
    {
      "epoch": 12,
      "train_loss": 0.7019376998477512,
      "val_loss": 0.6871339678764343
    },
    {
      "epoch": 13,
      "train_loss": 0.6850748226377699,
      "val_loss": 0.6189799308776855
    },
    {
      "epoch": 14,
      "train_loss": 0.6564740419387818,
      "val_loss": 0.6753837466239929
    },
    {
      "epoch": 15,
      "train_loss": 0.6343656370374892,
      "val_loss": 0.6381339430809021
    },
    {
      "epoch": 16,
      "train_loss": 0.6055290473832025,
      "val_loss": 0.5814887881278992
    },
    {
      "epoch": 17,
      "train_loss": 0.5885138122240702,
      "val_loss": 0.5470212697982788
    },
    {
      "epoch": 18,
      "train_loss": 0.5378465612729391,
      "val_loss": 0.5365827083587646
    },
    {
      "epoch": 19,
      "train_loss": 0.5616308797730339,
      "val_loss": 0.5047174096107483
    },
    {
      "epoch": 20,
      "train_loss": 0.5435021633572049,
      "val_loss": 0.5572128891944885
    },
    {
      "epoch": 21,
      "train_loss": 0.5212995767593384,
      "val_loss": 0.47710907459259033
    },
    {
      "epoch": 22,
      "train_loss": 0.48570749547746445,
      "val_loss": 0.5326237082481384
    },
    {
      "epoch": 23,
      "train_loss": 0.47772968848546343,
      "val_loss": 0.4815220236778259
    },
    {
      "epoch": 24,
      "train_loss": 0.4984182585610284,
      "val_loss": 0.4279056787490845
    },
    {
      "epoch": 25,
      "train_loss": 0.458404147889879,
      "val_loss": 0.4423450529575348
    },
    {
      "epoch": 26,
      "train_loss": 0.4583847158484989,
      "val_loss": 0.48912590742111206
    },
    {
      "epoch": 27,
      "train_loss": 0.4442947459220886,
      "val_loss": 0.4385117292404175
    },
    {
      "epoch": 28,
      "train_loss": 0.4293258537186517,
      "val_loss": 0.4707651436328888
    },
    {
      "epoch": 29,
      "train_loss": 0.41875846412446766,
      "val_loss": 0.3984597325325012
    },
    {
      "epoch": 30,
      "train_loss": 0.4128717181417677,
      "val_loss": 0.41525936126708984
    }
  ]
}